imgbbb/__init__.py
imgbbb/imgbbb.py
imgbbb-1.0.4.dist-info/LICENSE.md
imgbbb-1.0.4.dist-info/METADATA
imgbbb-1.0.4.dist-info/WHEEL
imgbbb-1.0.4.dist-info/entry_points.txt
imgbbb-1.0.4.dist-info/top_level.txt
imgbbb-1.0.4.dist-info/RECORD
