Metadata-Version: 2.1
Name: imgbbb
Version: 1.0.4
Summary: Imgbb uploader without API key
Home-page: https://github.com/OneFinalHug/imgbbb/
Author: OneFinalHug
Author-email: voidlillis@gmail.com
License: MIT
Keywords: imgbb_uploader,telegram,host,uploader,imgbb,image
Classifier: Programming Language :: Python :: 3
Classifier: License :: OSI Approved :: MIT License
Classifier: Operating System :: OS Independent
License-File: LICENSE.md
Requires-Dist: requests
Requires-Dist: colorclip
Requires-Dist: fake-useragent
Requires-Dist: requests-toolbelt
